runtime_dependency_manager/__init__.py
runtime_dependency_manager/manager.py
runtime_dependency_manager/version.py
tests/__init__.py
tests/test_runtime_dependency_manager.py
runtime_dependency_manager-0.1.9.dist-info/LICENSE
runtime_dependency_manager-0.1.9.dist-info/METADATA
runtime_dependency_manager-0.1.9.dist-info/WHEEL
runtime_dependency_manager-0.1.9.dist-info/top_level.txt
runtime_dependency_manager-0.1.9.dist-info/RECORD
