Metadata-Version: 2.1
Name: runtime_dependency_manager
Version: 0.1.9
Summary: A simple Python module for managing dependencies at runtime
Home-page: https://github.com/rabbitt/runtime_dependency_manager
Author: Carl Corliss
Author-email: rabbitt@gmail.com
License: GPL-3.0-or-later
Classifier: Programming Language :: Python
Classifier: Programming Language :: Python :: 3
Classifier: Programming Language :: Python :: 3.9
Classifier: License :: OSI Approved :: GNU General Public License v3 or later (GPLv3+)
Classifier: Operating System :: OS Independent
Requires-Python: >=3.9
License-File: LICENSE
Requires-Dist: packaging
